folderizer/__init__.py
folderizer-0.1.1.dist-info/LICENSE
folderizer-0.1.1.dist-info/METADATA
folderizer-0.1.1.dist-info/WHEEL
folderizer-0.1.1.dist-info/top_level.txt
folderizer-0.1.1.dist-info/RECORD
