Metadata-Version: 2.1
Name: folderizer
Version: 0.1.1
Summary: A Python script for file organization
Author: Roy J. Wignarajah
License: Apache-2.0
Project-URL: Homepage, https://github.com/rjwignar/folderizer
Project-URL: Changelog, https://github.com/rjwignar/folderizer/releases
Project-URL: Issues, https://github.com/rjwignar/folderizer/issues
Project-URL: CI, https://github.com/rjwignar/folderizer/actions
Classifier: License :: OSI Approved :: Apache Software License
Requires-Python: >=3.8
License-File: LICENSE
Provides-Extra: dev
Requires-Dist: ruff ; extra == 'dev'
Requires-Dist: mypy ; extra == 'dev'
Provides-Extra: test
Requires-Dist: pytest ; extra == 'test'
